torchrandom/__init__.py
torchrandom/tests/test_torch_random.py
torchrandom-0.0.1.dist-info/METADATA
torchrandom-0.0.1.dist-info/WHEEL
torchrandom-0.0.1.dist-info/licenses/LICENSE
torchrandom-0.0.1.dist-info/RECORD
