Metadata-Version: 2.1
Name: torchrandom
Version: 0.0.1
Summary: Pseudo random numbers for PyTorch
Project-URL: Homepage, https://github.com/mathinf/torchrandom
Project-URL: Issues, https://github.com/mathinf/torchrandom
Author-email: Thomas Viehmann <tv.code@beamnet.de>
License-File: LICENSE
Classifier: License :: OSI Approved :: MIT License
Classifier: Operating System :: OS Independent
Classifier: Programming Language :: Python :: 3
Requires-Python: >=3.10
